atcoder_auto_test/__init__.py
atcoder_auto_test/main.py
atcoder_auto_test-0.1.0.dist-info/WHEEL
atcoder_auto_test-0.1.0.dist-info/entry_points.txt
atcoder_auto_test-0.1.0.dist-info/METADATA
atcoder_auto_test-0.1.0.dist-info/RECORD
