Metadata-Version: 2.1
Name: atcoder-auto-test
Version: 0.1.0
Summary: 
Author: Kaji Keisuke
Author-email: kei.kyazikyazi@icloud.com
Requires-Python: >=3.8.0,<3.9.0
Classifier: Programming Language :: Python :: 3
Classifier: Programming Language :: Python :: 3.8
Requires-Dist: google-cloud-vision
Requires-Dist: numpy (>=1.24.1,<2.0.0)
Requires-Dist: online-judge-tools
Requires-Dist: pillow
